Metadata-Version: 2.1
Name: generax
Version: 0.1.2
Summary: Generative Models using Jax
Home-page: https://github.com/EddieCunningham/generax
Author: Edmond Cunningham
Author-email: edmondcunnin@cs.umass.edu
Classifier: Programming Language :: Python :: 3
Classifier: License :: OSI Approved :: MIT License
Classifier: Operating System :: OS Independent
Requires-Python: >=3.7
Requires-Dist: tqdm
Requires-Dist: optax
Requires-Dist: matplotlib
Requires-Dist: jax
Requires-Dist: einops
Requires-Dist: scikit-learn
Requires-Dist: equinox
Requires-Dist: diffrax
Requires-Dist: ott-jax
Requires-Dist: optimistix
